{
  "formatVersion": 1,
  "database": {
    "version": 5,
    "identityHash": "59f3eb11a51f5e13a1dfe527dfd29282",
    "entities": [
      {
        "tableName": "items",
        "createSql": "CREATE TABLE IF NOT EXISTS `${TABLE_NAME}` (`_id` TEXT NOT NULL, `text` TEXT NOT NULL, `description` TEXT NOT NULL, `dueDate` TEXT, `priority` INTEGER NOT NULL, `isCompleted` INTEGER NOT NULL, `latitude` REAL, `longitude` REAL, `syncStatus` TEXT NOT NULL, PRIMARY KEY(`_id`))",
        "fields": [
          {
            "fieldPath": "_id",
            "columnName": "_id",
            "affinity": "TEXT",
            "notNull": true
          },
          {
            "fieldPath": "text",
            "columnName": "text",
            "affinity": "TEXT",
            "notNull": true
          },
          {
            "fieldPath": "description",
            "columnName": "description",
            "affinity": "TEXT",
            "notNull": true
          },
          {
            "fieldPath": "dueDate",
            "columnName": "dueDate",
            "affinity": "TEXT",
            "notNull": false
          },
          {
            "fieldPath": "priority",
            "columnName": "priority",
            "affinity": "INTEGER",
            "notNull": true
          },
          {
            "fieldPath": "isCompleted",
            "columnName": "isCompleted",
            "affinity": "INTEGER",
            "notNull": true
          },
          {
            "fieldPath": "latitude",
            "columnName": "latitude",
            "affinity": "REAL",
            "notNull": false
          },
          {
            "fieldPath": "longitude",
            "columnName": "longitude",
            "affinity": "REAL",
            "notNull": false
          },
          {
            "fieldPath": "syncStatus",
            "columnName": "syncStatus",
            "affinity": "TEXT",
            "notNull": true
          }
        ],
        "primaryKey": {
          "autoGenerate": false,
          "columnNames": [
            "_id"
          ]
        },
        "indices": [],
        "foreignKeys": []
      }
    ],
    "views": [],
    "setupQueries": [
      "CREATE TABLE IF NOT EXISTS room_master_table (id INTEGER PRIMARY KEY,identity_hash TEXT)",
      "INSERT OR REPLACE INTO room_master_table (id,identity_hash) VALUES(42, '59f3eb11a51f5e13a1dfe527dfd29282')"
    ]
  }
}